CHANGES.txt
LICENSE.txt
MANIFEST.in
README.txt
setup.py
js/__init__.py
js.jquery_validate.egg-info/PKG-INFO
js.jquery_validate.egg-info/SOURCES.txt
js.jquery_validate.egg-info/dependency_links.txt
js.jquery_validate.egg-info/entry_points.txt
js.jquery_validate.egg-info/namespace_packages.txt
js.jquery_validate.egg-info/not-zip-safe
js.jquery_validate.egg-info/requires.txt
js.jquery_validate.egg-info/top_level.txt
js/jquery_validate/__init__.py
js/jquery_validate/test_jquery-validate.txt
js/jquery_validate/resources/.DS_Store
js/jquery_validate/resources/jquery.validate.js
js/jquery_validate/resources/jquery.validate.min.js