Metadata-Version: 1.0
Name: js.jquery-validate
Version: 1.11.0-1
Summary: Fanstatic packaging of validate for jQuery (jquery.validate.js)
Home-page: https://bitbucket.org/s_nikolai/js.jquery_validate
Author: Nikolai Sevostjanov
Author-email: nikolai.sevostjanov@gmail.com
License: BSD
Platform: UNKNOWN
